apicast/__init__.py
apicast/api.py
apicast/cli.py
apicast/core.py
apicast/format.py
apicast/util.py
apicast-0.9.0.dist-info/LICENSE
apicast-0.9.0.dist-info/METADATA
apicast-0.9.0.dist-info/WHEEL
apicast-0.9.0.dist-info/entry_points.txt
apicast-0.9.0.dist-info/top_level.txt
apicast-0.9.0.dist-info/RECORD
