Metadata-Version: 2.1
Name: apicast
Version: 0.9.0
Summary: Python client and HTTP service to access bee flight forecast information published by Deutscher Wetterdienst (DWD), the federal meteorological service in Germany.
Home-page: https://github.com/hiveeyes/apicast
Author: Andreas Motl
Author-email: andreas@hiveeyes.org
License: AGPL 3, EUPL 1.2
Keywords: honey bee apis mellifera flight forecast information dwd cdc deutscher wetterdienst climate data center weather opendata data acquisition transformation export geospatial temporal timeseries sensor network observation http rest api json markdown
Classifier: Programming Language :: Python
Classifier: Programming Language :: Python :: 3
Classifier: Programming Language :: Python :: 3.6
Classifier: Programming Language :: Python :: 3.7
Classifier: Programming Language :: Python :: 3.8
Classifier: Programming Language :: Python :: 3.9
Classifier: Programming Language :: Python :: 3.10
Classifier: Programming Language :: Python :: 3.11
Classifier: Programming Language :: Python :: 3.12
Classifier: Programming Language :: Python :: Implementation :: CPython
Classifier: Programming Language :: Python :: Implementation :: PyPy
Classifier: License :: OSI Approved :: European Union Public Licence 1.2 (EUPL 1.2)
Classifier: License :: OSI Approved :: GNU Affero General Public License v3 or later (AGPLv3+)
Classifier: Development Status :: 4 - Beta
Classifier: Environment :: Console
Classifier: Environment :: Web Environment
Classifier: Intended Audience :: Developers
Classifier: Intended Audience :: Education
Classifier: Intended Audience :: Information Technology
Classifier: Intended Audience :: Science/Research
Classifier: Topic :: Communications
Classifier: Topic :: Database
Classifier: Topic :: Internet
Classifier: Topic :: Scientific/Engineering :: Atmospheric Science
Classifier: Topic :: Scientific/Engineering :: GIS
Classifier: Topic :: Scientific/Engineering :: Human Machine Interfaces
Classifier: Topic :: Scientific/Engineering :: Information Analysis
Classifier: Topic :: Scientific/Engineering :: Interface Engine/Protocol Translator
Classifier: Topic :: Scientific/Engineering :: Visualization
Classifier: Topic :: Software Development :: Libraries
Classifier: Topic :: System :: Archiving
Classifier: Topic :: Text Processing
Classifier: Topic :: Utilities
Classifier: Operating System :: POSIX
Classifier: Operating System :: Unix
Classifier: Operating System :: MacOS
License-File: LICENSE
Requires-Dist: beautifulsoup4 <5,>=4
Requires-Dist: dateparser <2,>=0.7.4
Requires-Dist: docopt-ng <0.10,>=0.6
Requires-Dist: html-table-extractor <2,>=1
Requires-Dist: jsonpickle <4,>=2
Requires-Dist: munch <5,>=2.5
Requires-Dist: python-slugify <9,>=4
Requires-Dist: requests <3,>=2.25.2
Requires-Dist: tabulate <0.10,>=0.8
Requires-Dist: ttl-cache <2,>=1.6
Requires-Dist: tzlocal <6,>=2
Provides-Extra: service
Requires-Dist: fastapi <0.111,>=0.55.1 ; extra == 'service'
Requires-Dist: httpx <1 ; extra == 'service'
Requires-Dist: uvicorn <=0.29.0 ; extra == 'service'
